unitconvert/__init__.py
unitconvert/digitalunits.py
unitconvert/lengthunits.py
unitconvert/massunits.py
unitconvert/parentclasses.py
unitconvert/runconvert.py
unitconvert/temperatureunits.py
unitconvert/timeunits.py
unitconvert/volumeunits.py
unitconvert-1.0.4.dist-info/DESCRIPTION.rst
unitconvert-1.0.4.dist-info/METADATA
unitconvert-1.0.4.dist-info/RECORD
unitconvert-1.0.4.dist-info/WHEEL
unitconvert-1.0.4.dist-info/entry_points.txt
unitconvert-1.0.4.dist-info/metadata.json
unitconvert-1.0.4.dist-info/top_level.txt
