Metadata-Version: 1.1
Name: unitconvert
Version: 1.0.4
Summary: A command line tool and import library for performing unit conversions.
Home-page: https://github.com/skymaya/unitconvert
Author: Sky Maya
Author-email: skymaya@gmail.com
License: MIT
Keywords: unitconvert conversions units
Platform: UNKNOWN
Classifier: Development Status :: 5 - Production/Stable
Classifier: Environment :: Console
Classifier: Intended Audience :: Information Technology
Classifier: License :: OSI Approved :: MIT License
Classifier: Natural Language :: English
Classifier: Operating System :: Unix
Classifier: Programming Language :: Python :: 2
Classifier: Programming Language :: Python :: 3
Classifier: Topic :: Utilities
